my_verilog/__init__.py
my_verilog-0.1.3.dist-info/METADATA
my_verilog-0.1.3.dist-info/WHEEL
my_verilog-0.1.3.dist-info/top_level.txt
my_verilog-0.1.3.dist-info/RECORD
