Metadata-Version: 2.1
Name: my-verilog
Version: 0.1.3
Summary: a verilog package based on python3
Home-page: UNKNOWN
Author: 940746691
Author-email: 940746691@qq.com
License: UNKNOWN
Platform: UNKNOWN
Requires-Dist: pyverilog (==1.3.0)
